SwarmManagement/SwarmConfigs.py
SwarmManagement/SwarmManager.py
SwarmManagement/SwarmNetworks.py
SwarmManagement/SwarmSecrets.py
SwarmManagement/SwarmStacks.py
SwarmManagement/SwarmTools.py
SwarmManagement/SwarmVolumes.py
SwarmManagement/__init__.py
SwarmManagement/__main__.py
SwarmManagement-1.1.81.dist-info/LICENSE
SwarmManagement-1.1.81.dist-info/METADATA
SwarmManagement-1.1.81.dist-info/WHEEL
SwarmManagement-1.1.81.dist-info/entry_points.txt
SwarmManagement-1.1.81.dist-info/top_level.txt
SwarmManagement-1.1.81.dist-info/RECORD
