Metadata-Version: 2.1
Name: SwarmManagement
Version: 1.1.81
Summary: A library for managing Docker Swarm.
Home-page: https://github.com/hansehe/SwarmManagement
Author: Hans Erik Heggem
Author-email: hans.erik.heggem@gmail.com
License: UNKNOWN
Project-URL: Funding, https://donate.pypi.org
Project-URL: Say Thanks!, http://saythanks.io/to/example
Project-URL: Source, https://github.com/hansehe/SwarmManagement
Keywords: Docker Swarm Management
Platform: UNKNOWN
Classifier: Development Status :: 5 - Production/Stable
Classifier: Intended Audience :: Developers
Classifier: Topic :: Software Development :: Build Tools
Classifier: License :: OSI Approved :: MIT License
Classifier: Programming Language :: Python :: 2
Classifier: Programming Language :: Python :: 2.7
Classifier: Programming Language :: Python :: 3
Classifier: Programming Language :: Python :: 3.4
Classifier: Programming Language :: Python :: 3.5
Classifier: Programming Language :: Python :: 3.6
License-File: LICENSE
Requires-Dist: DockerBuildSystem (>=1.1.64)
Provides-Extra: dev
Requires-Dist: check-manifest ; extra == 'dev'
Provides-Extra: test
Requires-Dist: coverage ; extra == 'test'
